basicrta/__init__.py
basicrta/cluster.py
basicrta/combine.py
basicrta/contacts.py
basicrta/gibbs.py
basicrta/istarmap.py
basicrta/kinetics.py
basicrta/pwdensity.py
basicrta/util.py
basicrta/wdensity.py
basicrta/data/README.md
basicrta/data/__init__.py
basicrta/data/tm_dict.txt
basicrta/tests/__init__.py
basicrta/tests/datafiles.py
basicrta/tests/test_basicrta.py
basicrta/tests/test_cluster.py
basicrta/tests/test_combine_contacts.py
basicrta/tests/test_contacts.py
basicrta/tests/test_functions.py
basicrta/tests/test_gibbs.py
basicrta/tests/test_import.py
basicrta/tests/utils.py
basicrta/tests/data/prot_chol.gro
basicrta/tests/data/prot_chol.pdb
basicrta/tests/data/prot_chol.xtc
basicrta/tests/data/times.npy
basicrta-1.1.3.dist-info/licenses/LICENSE
devtools/scripts/create_conda_env.py
docs/source/conf.py
scripts/get_rerun_residues.py
scripts/setup.py
basicrta-1.1.3.dist-info/METADATA
basicrta-1.1.3.dist-info/WHEEL
basicrta-1.1.3.dist-info/top_level.txt
basicrta-1.1.3.dist-info/RECORD
