Metadata-Version: 2.4
Name: basicrta
Version: 1.1.3
Summary: A package to extract binding kinetics from molecular dynamics simulations
Author-email: Ricky Sexton <risexto878@gmail.com>
Maintainer-email: Ricky Sexton <risexto878@gmail.com>
License-Expression: GPL-3.0-or-later
Project-URL: source, https://github.com/becksteinlab/basicrta
Project-URL: documentation, https://basicrta.readthedocs.io
Keywords: molecular simulations
Requires-Python: >=3.10
License-File: LICENSE
Requires-Dist: MDAnalysis>=2.0.0
Requires-Dist: numpy
Requires-Dist: matplotlib
Requires-Dist: scikit-learn
Requires-Dist: scipy
Requires-Dist: tqdm
Requires-Dist: seaborn
Provides-Extra: test
Requires-Dist: pytest>=8.0; extra == "test"
Requires-Dist: pytest-xdist>=2.5; extra == "test"
Requires-Dist: pytest-cov>=3.0; extra == "test"
Provides-Extra: doc
Requires-Dist: sphinx; extra == "doc"
Requires-Dist: sphinx_rtd_theme; extra == "doc"
Dynamic: license-file
